aim/__init__.py
aim/__version__.py
aim/logger.py
aim/artifacts/__init__.py
aim/artifacts/artifact.py
aim/artifacts/artifact_writer.py
aim/artifacts/map.py
aim/artifacts/metric.py
aim/artifacts/model.py
aim/artifacts/record.py
aim/artifacts/record_writer.py
aim/artifacts/utils.py
aim/artifacts/proto/__init__.py
aim/artifacts/proto/base_pb2.py
aim/artifacts/proto/metric_pb2.py
aim/cli/__init__.py
aim/cli/cli.py
aim/cli/configs.py
aim/cli/commit/__init__.py
aim/cli/commit/commands.py
aim/cli/config/__init__.py
aim/cli/config/commands.py
aim/cli/de/__init__.py
aim/cli/de/commands.py
aim/cli/experiment/__init__.py
aim/cli/experiment/commands.py
aim/cli/init/__init__.py
aim/cli/init/commands.py
aim/cli/reset/__init__.py
aim/cli/reset/commands.py
aim/cli/status/__init__.py
aim/cli/status/commands.py
aim/cli/version/__init__.py
aim/cli/version/commands.py
aim/engine/__init__.py
aim/engine/aim_container.py
aim/engine/aim_profile.py
aim/engine/aim_repo.py
aim/engine/configs.py
aim/engine/types.py
aim/engine/utils.py
aim/sdk/__init__.py
aim/sdk/init.py
aim/sdk/track.py
aim/version_control/__init__.py
aim/version_control/base.py
aim/version_control/factory.py
aim/version_control/git.py
examples/__init__.py
examples/keras_vgg_save.py
examples/pytorch_model_load.py
examples/pytorch_model_save.py
examples/pytorch_track_all.py
examples/pytorch_track_metrics.py
examples/pytorch_track_params.py
examples/retrieve_metrics.py
examples/track_map.py
aimstack-2.0.0.dist-info/LICENSE
aimstack-2.0.0.dist-info/METADATA
aimstack-2.0.0.dist-info/WHEEL
aimstack-2.0.0.dist-info/entry_points.txt
aimstack-2.0.0.dist-info/top_level.txt
aimstack-2.0.0.dist-info/RECORD
