Metadata-Version: 2.1
Name: aimstack
Version: 2.0.0
Summary: Version control for AI
Home-page: UNKNOWN
License: UNKNOWN
Platform: UNKNOWN
Classifier: License :: OSI Approved :: MIT License
Classifier: Programming Language :: Python
Classifier: Programming Language :: Python :: 3
Classifier: Programming Language :: Python :: 3.7
Classifier: Programming Language :: Python :: Implementation :: PyPy
Requires-Python: >=3.5.2
Requires-Dist: click (>=6.7)
Requires-Dist: paramiko (>=2.6.0)
Requires-Dist: GitPython (>=3.0.4)
Requires-Dist: requests (>=2.0.0)
Requires-Dist: psutil (>=5.6.7)
Requires-Dist: py3nvml (>=0.2.5)
Requires-Dist: docker (>=4.1.0)
Requires-Dist: aimrecords (>=0.0.3)
Requires-Dist: protobuf (>=3.11.0)
